{
  "competition": "🏆 FIFA World Cup 2026",

  "currentMatch": {
    "home": "USA",
    "away": "BIH",
    "homeFlag": "https://raw.githubusercontent.com/ahmedsala71225-cell/worldcup2026/refs/heads/main/flags/USA.jpg",
    "awayFlag": "https://raw.githubusercontent.com/ahmedsala71225-cell/worldcup2026/refs/heads/main/flags/BIH.jpg",

    "scoreHome": "2",
    "scoreAway": "0",

    "status": "⚪ FINISHED",
    "showShape": "1",
    "phase": "",
    "kickoff": "",
    "secondHalfKickoff": "",

    "date": "2026-06-29",
    "time": ""
  },

  "nextMatch": {
    "home": "ESP",
    "away": "AUT",
    "homeFlag": "https://raw.githubusercontent.com/ahmedsala71225-cell/worldcup2026/refs/heads/main/flags/ESP.jpg",
    "awayFlag": "https://raw.githubusercontent.com/ahmedsala71225-cell/worldcup2026/refs/heads/main/flags/AUT.jpg",
    "status": "Next",
    "date": "2026-06-23",
    "time": "10:00 PM"
  }
}
